wavespeed/__init__.py
wavespeed/__main__.py
wavespeed/server.py
mcp_server_wavespeed-0.1.0.dist-info/METADATA
mcp_server_wavespeed-0.1.0.dist-info/WHEEL
mcp_server_wavespeed-0.1.0.dist-info/entry_points.txt
mcp_server_wavespeed-0.1.0.dist-info/top_level.txt
mcp_server_wavespeed-0.1.0.dist-info/RECORD
