Metadata-Version: 2.4
Name: mcp-server-wavespeed
Version: 0.1.0
Requires-Dist: requests
Requires-Dist: pydantic
Requires-Dist: python-dotenv
Dynamic: requires-dist
